{
  "forms": {
    "P---------": [
      [
        "010213",
        "πρός"
      ],
      [
        "010306",
        "πρός"
      ],
      [
        "010311",
        "πρός"
      ],
      [
        "010314",
        "πρός"
      ],
      [
        "010315",
        "πρός"
      ],
      [
        "010316",
        "πρός"
      ],
      [
        "010407",
        "πρός"
      ],
      [
        "010529",
        "πρός"
      ],
      [
        "010602",
        "πρός"
      ],
      [
        "010716",
        "πρός"
      ],
      [
        "011007",
        "πρός"
      ],
      [
        "011014",
        "πρός"
      ],
      [
        "011129",
        "πρός"
      ],
      [
        "011303",
        "πρός"
      ],
      [
        "011331",
        "πρός"
      ],
      [
        "011357",
        "πρός"
      ],
      [
        "011426",
        "πρός"
      ],
      [
        "011429",
        "πρός"
      ],
      [
        "011430",
        "πρός"
      ],
      [
        "011715",
        "πρός"
      ],
      [
        "011909",
        "πρός"
      ],
      [
        "011915",
        "πρός"
      ],
      [
        "012133",
        "πρός"
      ],
      [
        "012135",
        "πρός"
      ],
      [
        "012138",
        "πρός"
      ],
      [
        "012306",
        "πρός"
      ],
      [
        "012335",
        "πρός"
      ],
      [
        "012338",
        "πρός"
      ],
      [
        "012510",
        "πρός"
      ],
      [
        "012537",
        "πρός"
      ],
      [
        "012540",
        "πρός"
      ],
      [
        "012613",
        "πρός"
      ],
      [
        "012615",
        "πρός"
      ],
      [
        "012619",
        "πρός"
      ],
      [
        "012619",
        "πρός"
      ],
      [
        "012641",
        "πρός"
      ],
      [
        "012646",
        "πρός"
      ],
      [
        "012658",
        "πρός"
      ],
      [
        "012705",
        "πρός"
      ],
      [
        "012715",
        "πρός"
      ],
      [
        "012720",
        "πρός"
      ],
      [
        "012763",
        "πρός"
      ],
      [
        "020106",
        "πρός"
      ],
      [
        "020128",
        "πρός"
      ],
      [
        "020133",
        "πρός"
      ],
      [
        "020134",
        "πρός"
      ],
      [
        "020141",
        "πρός"
      ],
      [
        "020201",
        "πρός"
      ],
      [
        "020203",
        "πρός"
      ],
      [
        "020204",
        "πρός"
      ],
      [
        "020214",
        "πρός"
      ],
      [
        "020308",
        "πρός"
      ],
      [
        "020309",
        "πρός"
      ],
      [
        "020314",
        "πρός"
      ],
      [
        "020332",
        "πρός"
      ],
      [
        "020402",
        "πρός"
      ],
      [
        "020402",
        "πρός"
      ],
      [
        "020501",
        "πρός"
      ],
      [
        "020512",
        "πρός"
      ],
      [
        "020516",
        "πρός"
      ],
      [
        "020520",
        "πρός"
      ],
      [
        "020523",
        "πρός"
      ],
      [
        "020604",
        "πρός"
      ],
      [
        "020626",
        "πρός"
      ],
      [
        "020631",
        "πρός"
      ],
      [
        "020646",
        "πρός"
      ],
      [
        "020649",
        "πρός"
      ],
      [
        "020652",
        "πρός"
      ],
      [
        "020702",
        "πρός"
      ],
      [
        "020726",
        "πρός"
      ],
      [
        "020817",
        "πρός"
      ],
      [
        "020911",
        "πρός"
      ],
      [
        "020915",
        "πρός"
      ],
      [
        "020915",
        "πρός"
      ],
      [
        "020917",
        "πρός"
      ],
      [
        "020918",
        "πρός"
      ],
      [
        "020920",
        "πρός"
      ],
      [
        "020920",
        "πρός"
      ],
      [
        "020921",
        "πρός"
      ],
      [
        "020935",
        "πρός"
      ],
      [
        "021002",
        "πρός"
      ],
      [
        "021006",
        "πρός"
      ],
      [
        "021008",
        "πρός"
      ],
      [
        "021015",
        "πρός"
      ],
      [
        "021027",
        "πρός"
      ],
      [
        "021051",
        "πρός"
      ],
      [
        "021102",
        "πρός"
      ],
      [
        "021105",
        "πρός"
      ],
      [
        "021108",
        "πρός"
      ],
      [
        "021128",
        "πρός"
      ],
      [
        "021132",
        "πρός"
      ],
      [
        "021203",
        "πρός"
      ],
      [
        "021205",
        "πρός"
      ],
      [
        "021207",
        "πρός"
      ],
      [
        "021208",
        "πρός"
      ],
      [
        "021213",
        "πρός"
      ],
      [
        "021214",
        "πρός"
      ],
      [
        "021219",
        "πρός"
      ],
      [
        "021323",
        "πρός"
      ],
      [
        "021405",
        "πρός"
      ]
    ]
  },
  "occurences": 696,
  "definitions": {
    "mounce": "from; met. for the benefit of, Acts 27:34; with a dative, near, by, at, by the side of, in the vicinity of, Mk. 5:11; Lk. 19:37; with an accusative, used of the place to which anything tends, to, unto, towards, Mt. 2:12; 3:5, 13; at, close upon, Mt. 3:10; Mk. 5:22; near to, in the vicinity of, Mk. 6:45; after verbs of speaking, praying, answering to a charge, etc., to, Mt. 3:15; 27:14; of place where, with, in, among, by, at, etc., Mt. 26:55; Mk. 11:4; Lk. 1:80; of time, for, during, Lk. 8:13; 1 Cor. 7:5; near, towards, Lk. 24:29; of the end, object, purpose for which an action is exerted, or to which any quality, etc., has reference, to, Jn. 4:35; Acts 3:10; 27:12; before an infin. with τό, in order to, that, in order that, Mt. 6:1; 13:30; 26:12; so as to, so that, Mt. 5:28; of the relation which any action, state, quality, etc., bears to any person or thing, in relation to, of, concerning, in respect to, with reference to, Mt. 19:8; Lk. 12:41; 18:1; 20:19; as it respects, as it concerns, with relation to, Mt. 27:4; Jn. 21:22, 23; according to, in conformity with, Lk. 12:47; 2 Cor. 5:10; in comparison with, Rom. 8:18; in attention to, Eph. 3:4; of the actions, dispositions, etc., exhibited with respect to any one, whether friendly, towards, Gal. 6:10; Eph. 6:9; or unfriendly, with, against, Lk. 23:12; Acts 23:30; after verbs signifying to converse, dispute, make a covenant, etc., with, Lk. 24:14; Acts 2:7; 3:25"
  }
}