{
  "forms": {
    "D---------": [
      [
        "010408",
        "πάλιν"
      ],
      [
        "010409",
        "πάλιν"
      ],
      [
        "010534",
        "πάλιν"
      ],
      [
        "011346",
        "πάλιν"
      ],
      [
        "011348",
        "πάλιν"
      ],
      [
        "011820",
        "πάλιν"
      ],
      [
        "011925",
        "πάλιν"
      ],
      [
        "012006",
        "πάλιν"
      ],
      [
        "012137",
        "πάλιν"
      ],
      [
        "012202",
        "πάλιν"
      ],
      [
        "012205",
        "πάλιν"
      ],
      [
        "012643",
        "πάλιν"
      ],
      [
        "012644",
        "πάλιν"
      ],
      [
        "012645",
        "πάλιν"
      ],
      [
        "012645",
        "πάλιν"
      ],
      [
        "012673",
        "πάλιν"
      ],
      [
        "012751",
        "πάλιν"
      ],
      [
        "020202",
        "πάλιν"
      ],
      [
        "020214",
        "πάλιν"
      ],
      [
        "020302",
        "πάλιν"
      ],
      [
        "020321",
        "πάλιν"
      ],
      [
        "020402",
        "πάλιν"
      ],
      [
        "020522",
        "πάλιν"
      ],
      [
        "020715",
        "πάλιν"
      ],
      [
        "020732",
        "πάλιν"
      ],
      [
        "020802",
        "πάλιν"
      ],
      [
        "020814",
        "πάλιν"
      ],
      [
        "020826",
        "πάλιν"
      ],
      [
        "021002",
        "πάλιν"
      ],
      [
        "021002",
        "πάλιν"
      ],
      [
        "021011",
        "πάλιν"
      ],
      [
        "021025",
        "πάλιν"
      ],
      [
        "021033",
        "πάλιν"
      ],
      [
        "021104",
        "πάλιν"
      ],
      [
        "021128",
        "πάλιν"
      ],
      [
        "021205",
        "πάλιν"
      ],
      [
        "021440",
        "πάλιν"
      ],
      [
        "021441",
        "πάλιν"
      ],
      [
        "021462",
        "πάλιν"
      ],
      [
        "021470",
        "πάλιν"
      ],
      [
        "021471",
        "πάλιν"
      ],
      [
        "021471",
        "πάλιν"
      ],
      [
        "021505",
        "πάλιν"
      ],
      [
        "021513",
        "πάλιν"
      ],
      [
        "021514",
        "πάλιν"
      ],
      [
        "030644",
        "πάλιν"
      ],
      [
        "031321",
        "πάλιν"
      ],
      [
        "032321",
        "πάλιν"
      ],
      [
        "040136",
        "πάλιν"
      ],
      [
        "040404",
        "πάλιν"
      ],
      [
        "040414",
        "πάλιν"
      ],
      [
        "040447",
        "πάλιν"
      ],
      [
        "040501",
        "πάλιν"
      ],
      [
        "040616",
        "πάλιν"
      ],
      [
        "040813",
        "πάλιν"
      ],
      [
        "040822",
        "πάλιν"
      ],
      [
        "040916",
        "πάλιν"
      ],
      [
        "040918",
        "πάλιν"
      ],
      [
        "040928",
        "πάλιν"
      ],
      [
        "041008",
        "πάλιν"
      ],
      [
        "041018",
        "πάλιν"
      ],
      [
        "041019",
        "πάλιν"
      ],
      [
        "041020",
        "πάλιν"
      ],
      [
        "041032",
        "πάλιν"
      ],
      [
        "041040",
        "πάλιν"
      ],
      [
        "041041",
        "πάλιν"
      ],
      [
        "041108",
        "πάλιν"
      ],
      [
        "041109",
        "πάλιν"
      ],
      [
        "041139",
        "πάλιν"
      ],
      [
        "041229",
        "πάλιν"
      ],
      [
        "041240",
        "πάλιν"
      ],
      [
        "041313",
        "πάλιν"
      ],
      [
        "041404",
        "πάλιν"
      ],
      [
        "041617",
        "πάλιν"
      ],
      [
        "041618",
        "πάλιν"
      ],
      [
        "041620",
        "πάλιν"
      ],
      [
        "041623",
        "πάλιν"
      ],
      [
        "041629",
        "πάλιν"
      ],
      [
        "041808",
        "πάλιν"
      ],
      [
        "041828",
        "πάλιν"
      ],
      [
        "041834",
        "πάλιν"
      ],
      [
        "041839",
        "πάλιν"
      ],
      [
        "041901",
        "πάλιν"
      ],
      [
        "041905",
        "πάλιν"
      ],
      [
        "041910",
        "πάλιν"
      ],
      [
        "041938",
        "πάλιν"
      ],
      [
        "042011",
        "πάλιν"
      ],
      [
        "042022",
        "πάλιν"
      ],
      [
        "042027",
        "πάλιν"
      ],
      [
        "042102",
        "πάλιν"
      ],
      [
        "042117",
        "πάλιν"
      ],
      [
        "051016",
        "πάλιν"
      ],
      [
        "051111",
        "πάλιν"
      ],
      [
        "051733",
        "πάλιν"
      ],
      [
        "051822",
        "πάλιν"
      ],
      [
        "052729",
        "πάλιν"
      ],
      [
        "060816",
        "πάλιν"
      ],
      [
        "061124",
        "πάλιν"
      ],
      [
        "061511",
        "πάλιν"
      ],
      [
        "061512",
        "πάλιν"
      ]
    ]
  },
  "occurences": 139,
  "definitions": {
    "mounce": "pr. back; again, back again, Jn. 10:17; Acts 10:16; 11:10; again by repetition, Mt. 26:43; again in continuation, further, Mt. 5:33; 13:44, 45, 47, 18:19; again, on the other hand, 1 Jn. 2:8"
  }
}