{
  "forms": {
    "A-----APM-": [
      [
        "012013",
        "ἴσους"
      ]
    ],
    "A-----NPF-": [
      [
        "021457",
        "ἴσαι"
      ]
    ],
    "A-----NSF-": [
      [
        "021460",
        "ἴση"
      ]
    ],
    "A-----APN-": [
      [
        "030635",
        "ἴσα"
      ],
      [
        "110207",
        "ἴσα"
      ]
    ],
    "A-----ASM-": [
      [
        "040519",
        "ἴσον"
      ]
    ],
    "A-----ASF-": [
      [
        "051118",
        "ἴσην"
      ]
    ],
    "A-----NPN-": [
      [
        "272117",
        "ἴσα"
      ]
    ]
  },
  "occurences": 8,
  "definitions": {
    "mounce": "equal, like, Mt. 20:12; Lk. 6:34; on an equality, Phil. 2:6; met. correspondent, consistent, Mk. 14:56, 59"
  }
}