{
  "forms": {
    "A-----APM-": [
      [
        "012013",
        "ἴσους"
      ]
    ],
    "A-----NPF-": [
      [
        "021457",
        "ἴσαι"
      ]
    ],
    "A-----NSF-": [
      [
        "021460",
        "ἴση"
      ]
    ],
    "A-----APN-": [
      [
        "030635",
        "ἴσα"
      ],
      [
        "110207",
        "ἴσα"
      ]
    ],
    "A-----ASM-": [
      [
        "040519",
        "ἴσον"
      ]
    ],
    "A-----ASF-": [
      [
        "051118",
        "ἴσην"
      ]
    ],
    "A-----NPN-": [
      [
        "272117",
        "ἴσα"
      ]
    ]
  },
  "occurences": 8
}