{
  "forms": {
    "N-----NSM-": [
      [
        "010530",
        "ὀφθαλμός"
      ],
      [
        "010623",
        "ὀφθαλμός"
      ],
      [
        "010623",
        "ὀφθαλμός"
      ],
      [
        "010624",
        "ὀφθαλμός"
      ],
      [
        "011810",
        "ὀφθαλμός"
      ],
      [
        "012016",
        "ὀφθαλμός"
      ],
      [
        "020723",
        "ὀφθαλμός"
      ],
      [
        "020948",
        "ὀφθαλμός"
      ],
      [
        "031135",
        "ὀφθαλμός"
      ],
      [
        "031135",
        "ὀφθαλμός"
      ],
      [
        "070210",
        "ὀφθαλμός"
      ],
      [
        "071217",
        "ὀφθαλμός"
      ],
      [
        "071218",
        "ὀφθαλμός"
      ],
      [
        "071222",
        "ὀφθαλμός"
      ],
      [
        "270108",
        "ὀφθαλμός"
      ]
    ],
    "N-----ASM-": [
      [
        "010539",
        "ὀφθαλμόν"
      ]
    ],
    "N-----GSM-": [
      [
        "010539",
        "ὀφθαλμοῦ"
      ],
      [
        "010705",
        "ὀφθαλμοῦ"
      ],
      [
        "010706",
        "ὀφθαλμοῦ"
      ],
      [
        "010706",
        "ὀφθαλμοῦ"
      ],
      [
        "030643",
        "ὀφθαλμοῦ"
      ],
      [
        "071553",
        "ὀφθαλμοῦ"
      ]
    ],
    "N-----DSM-": [
      [
        "010704",
        "ὀφθαλμῷ"
      ],
      [
        "010704",
        "ὀφθαλμῷ"
      ],
      [
        "010705",
        "ὀφθαλμῷ"
      ],
      [
        "030642",
        "ὀφθαλμῷ"
      ],
      [
        "030642",
        "ὀφθαλμῷ"
      ],
      [
        "030643",
        "ὀφθαλμῷ"
      ],
      [
        "030643",
        "ὀφθαλμῷ"
      ],
      [
        "030643",
        "ὀφθαλμῷ"
      ]
    ],
    "N-----GPM-": [
      [
        "010930",
        "ὀφθαλμῶν"
      ],
      [
        "031943",
        "ὀφθαλμῶν"
      ],
      [
        "050110",
        "ὀφθαλμῶν"
      ],
      [
        "050909",
        "ὀφθαλμῶν"
      ],
      [
        "050919",
        "ὀφθαλμῶν"
      ],
      [
        "060319",
        "ὀφθαλμῶν"
      ],
      [
        "230217",
        "ὀφθαλμῶν"
      ],
      [
        "270407",
        "ὀφθαλμῶν"
      ],
      [
        "270409",
        "ὀφθαλμῶν"
      ],
      [
        "270801",
        "ὀφθαλμῶν"
      ],
      [
        "272105",
        "ὀφθαλμῶν"
      ]
    ],
    "N-----NPM-": [
      [
        "010931",
        "ὀφθαλμοί"
      ],
      [
        "011317",
        "ὀφθαλμοί"
      ],
      [
        "012034",
        "ὀφθαλμοί"
      ],
      [
        "012644",
        "ὀφθαλμοί"
      ],
      [
        "021441",
        "ὀφθαλμοί"
      ],
      [
        "030231",
        "ὀφθαλμοί"
      ],
      [
        "030421",
        "ὀφθαλμοί"
      ],
      [
        "031024",
        "ὀφθαλμοί"
      ],
      [
        "032417",
        "ὀφθαλμοί"
      ],
      [
        "032432",
        "ὀφθαλμοί"
      ],
      [
        "040911",
        "ὀφθαλμοί"
      ],
      [
        "061111",
        "ὀφθαλμοί"
      ],
      [
        "210313",
        "ὀφθαλμοί"
      ],
      [
        "270115",
        "ὀφθαλμοί"
      ],
      [
        "271913",
        "ὀφθαλμοί"
      ]
    ],
    "N-----APM-": [
      [
        "011316",
        "ὀφθαλμούς"
      ],
      [
        "011709",
        "ὀφθαλμούς"
      ],
      [
        "011810",
        "ὀφθαλμούς"
      ],
      [
        "020819",
        "ὀφθαλμούς"
      ],
      [
        "020826",
        "ὀφθαλμούς"
      ],
      [
        "020948",
        "ὀφθαλμούς"
      ],
      [
        "030621",
        "ὀφθαλμούς"
      ],
      [
        "031624",
        "ὀφθαλμούς"
      ],
      [
        "031814",
        "ὀφθαλμούς"
      ],
      [
        "040436",
        "ὀφθαλμούς"
      ],
      [
        "040606",
        "ὀφθαλμούς"
      ],
      [
        "040907",
        "ὀφθαλμούς"
      ],
      [
        "040912",
        "ὀφθαλμούς"
      ],
      [
        "040915",
        "ὀφθαλμούς"
      ],
      [
        "040916",
        "ὀφθαλμούς"
      ],
      [
        "040918",
        "ὀφθαλμούς"
      ],
      [
        "040922",
        "ὀφθαλμούς"
      ],
      [
        "040927",
        "ὀφθαλμούς"
      ],
      [
        "040931",
        "ὀφθαλμούς"
      ],
      [
        "040933",
        "ὀφθαλμούς"
      ],
      [
        "041022",
        "ὀφθαλμούς"
      ],
      [
        "041138",
        "ὀφθαλμούς"
      ],
      [
        "041142",
        "ὀφθαλμούς"
      ],
      [
        "041241",
        "ὀφθαλμούς"
      ],
      [
        "041702",
        "ὀφθαλμούς"
      ],
      [
        "050941",
        "ὀφθαλμούς"
      ],
      [
        "052619",
        "ὀφθαλμούς"
      ],
      [
        "052828",
        "ὀφθαλμούς"
      ],
      [
        "061109",
        "ὀφθαλμούς"
      ],
      [
        "090302",
        "ὀφθαλμούς"
      ],
      [
        "090416",
        "ὀφθαλμούς"
      ],
      [
        "100119",
        "ὀφθαλμούς"
      ],
      [
        "220215",
        "ὀφθαλμούς"
      ],
      [
        "230212",
        "ὀφθαλμούς"
      ],
      [
        "270219",
        "ὀφθαλμούς"
      ],
      [
        "270319",
        "ὀφθαλμούς"
      ],
      [
        "270507",
        "ὀφθαλμούς"
      ]
    ],
    "N-----DPM-": [
      [
        "011316",
        "ὀφθαλμοῖς"
      ],
      [
        "012143",
        "ὀφθαλμοῖς"
      ],
      [
        "021212",
        "ὀφθαλμοῖς"
      ],
      [
        "041241",
        "ὀφθαλμοῖς"
      ],
      [
        "052828",
        "ὀφθαλμοῖς"
      ],
      [
        "190414",
        "ὀφθαλμοῖς"
      ],
      [
        "230102",
        "ὀφθαλμοῖς"
      ]
    ]
  },
  "occurences": 100,
  "definitions": {
    "mounce": "an eye, Mt. 5:29, 38; 6:23; 7:3, 4, 5; ὀφθαλμὸς πονηρός, an evil eye, an envious eye, envy, Mt. 20:15; Mk. 7:22; met. the intellectual eye, Mt. 13:15; Mk. 8:18; Jn. 12:40; Acts 26:18"
  }
}