{
  "forms": {
    "V--PAPVPM-": [
      [
        "012325",
        "καταπίνοντες"
      ]
    ],
    "V-3API-S--": [
      [
        "071555",
        "κατεπόθη"
      ]
    ],
    "V-3APS-S--": [
      [
        "080208",
        "καταποθῇ"
      ],
      [
        "080505",
        "καταποθῇ"
      ]
    ],
    "V-3API-P--": [
      [
        "191130",
        "κατεπόθησαν"
      ]
    ],
    "V--AAN----": [
      [
        "210509",
        "καταπιεῖν"
      ]
    ],
    "V-3AAI-S--": [
      [
        "271217",
        "κατέπιε(ν)"
      ]
    ]
  },
  "occurences": 7
}