{
  "forms": {
    "N-----DPM-": [
      [
        "010707",
        "κυσί(ν)"
      ]
    ],
    "N-----NPM-": [
      [
        "031622",
        "κύνες"
      ],
      [
        "272216",
        "κύνες"
      ]
    ],
    "N-----APM-": [
      [
        "110303",
        "κύνας"
      ]
    ],
    "N-----NSM-": [
      [
        "220301",
        "κύων"
      ]
    ]
  },
  "occurences": 5,
  "definitions": {
    "mounce": "a dog, Mt. 7:6; Lk. 16:21; 2 Pet. 2:22; met. a dog, a religious corrupter, Phil. 3:2; miscreant, Rev. 22:15*"
  }
}