{
  "forms": {
    "V-3AAI-S--": [
      [
        "010819",
        "ἐκέλευσε(ν)"
      ],
      [
        "011410",
        "ἐκέλευσε(ν)"
      ],
      [
        "011826",
        "ἐκέλευσε(ν)"
      ],
      [
        "012759",
        "ἐκέλευσε(ν)"
      ],
      [
        "031841",
        "ἐκέλευσε(ν)"
      ],
      [
        "050535",
        "ἐκέλευσε(ν)"
      ],
      [
        "050839",
        "ἐκέλευσε(ν)"
      ],
      [
        "051220",
        "ἐκέλευσε(ν)"
      ],
      [
        "052134",
        "ἐκέλευσε(ν)"
      ],
      [
        "052135",
        "ἐκέλευσε(ν)"
      ],
      [
        "052225",
        "ἐκέλευσε(ν)"
      ],
      [
        "052301",
        "ἐκέλευσε(ν)"
      ],
      [
        "052311",
        "ἐκέλευσε(ν)"
      ],
      [
        "052507",
        "ἐκέλευσε(ν)"
      ],
      [
        "052744",
        "ἐκέλευσε(ν)"
      ]
    ],
    "V--AAPNSM-": [
      [
        "011420",
        "κελεύσας"
      ],
      [
        "052401",
        "κελεύσας"
      ]
    ],
    "V-2AAD-S--": [
      [
        "011429",
        "κέλευσον"
      ],
      [
        "012765",
        "κέλευσον"
      ]
    ],
    "V--AAPNPM-": [
      [
        "050416",
        "κελεύσαντες"
      ]
    ],
    "V-3IAI-P--": [
      [
        "051623",
        "ἐκέλευον"
      ]
    ],
    "V-2PAI-S--": [
      [
        "052304",
        "κελεύεις"
      ]
    ],
    "V-1AAI-S--": [
      [
        "052518",
        "ἐκέλευσα"
      ],
      [
        "052522",
        "ἐκέλευσα"
      ]
    ],
    "V--AAPGSM-": [
      [
        "052524",
        "κελεύσαντος"
      ]
    ]
  },
  "occurences": 25
}