{
  "forms": {
    "N-----ASF-": [
      [
        "010523",
        "γέενναν"
      ],
      [
        "010530",
        "γέενναν"
      ],
      [
        "010531",
        "γέενναν"
      ],
      [
        "011810",
        "γέενναν"
      ],
      [
        "020945",
        "γέενναν"
      ],
      [
        "020947",
        "γέενναν"
      ],
      [
        "020948",
        "γέενναν"
      ],
      [
        "031206",
        "γέενναν"
      ]
    ],
    "N-----DSF-": [
      [
        "011029",
        "γεέννῃ"
      ]
    ],
    "N-----GSF-": [
      [
        "012316",
        "γεέννης"
      ],
      [
        "012334",
        "γεέννης"
      ],
      [
        "200307",
        "γεέννης"
      ]
    ]
  },
  "occurences": 12
}