{
  "forms": {
    "V--PAPNPM-": [
      [
        "011109",
        "φοροῦντες"
      ]
    ],
    "V--PAPNSM-": [
      [
        "041906",
        "φορῶν"
      ]
    ],
    "V-3PAI-S--": [
      [
        "061305",
        "φορεῖ"
      ]
    ],
    "V-1AAI-P--": [
      [
        "071550",
        "ἐφορέσαμεν"
      ]
    ],
    "V-1FAI-P--": [
      [
        "071550",
        "φορέσομεν"
      ]
    ],
    "V--PAPASM-": [
      [
        "200204",
        "φοροῦντα"
      ]
    ]
  },
  "occurences": 6,
  "definitions": {
    "mounce": "to bear; to wear, Mt. 11:8; Jn. 19:5; Rom. 13:4; 1 Cor. 15:49; Jas. 2:3"
  }
}