{
  "forms": {
    "N-----ASN-": [
      [
        "011325",
        "σπέρμα"
      ],
      [
        "011328",
        "σπέρμα"
      ],
      [
        "011338",
        "σπέρμα"
      ],
      [
        "012225",
        "σπέρμα"
      ],
      [
        "012226",
        "σπέρμα"
      ],
      [
        "021220",
        "σπέρμα"
      ],
      [
        "021221",
        "σπέρμα"
      ],
      [
        "021222",
        "σπέρμα"
      ],
      [
        "021223",
        "σπέρμα"
      ],
      [
        "032029",
        "σπέρμα"
      ],
      [
        "060909",
        "σπέρμα"
      ],
      [
        "060930",
        "σπέρμα"
      ]
    ],
    "N-----GPN-": [
      [
        "011333",
        "σπερμάτων"
      ],
      [
        "020432",
        "σπερμάτων"
      ],
      [
        "071539",
        "σπερμάτων"
      ]
    ],
    "N-----NSN-": [
      [
        "011339",
        "σπέρμα"
      ],
      [
        "040834",
        "σπέρμα"
      ],
      [
        "040838",
        "σπέρμα"
      ],
      [
        "050707",
        "σπέρμα"
      ],
      [
        "060419",
        "σπέρμα"
      ],
      [
        "060908",
        "σπέρμα"
      ],
      [
        "060908",
        "σπέρμα"
      ],
      [
        "081123",
        "σπέρμα"
      ],
      [
        "090320",
        "σπέρμα"
      ],
      [
        "090401",
        "σπέρμα"
      ],
      [
        "191119",
        "σπέρμα"
      ],
      [
        "230310",
        "σπέρμα"
      ]
    ],
    "N-----DSN-": [
      [
        "030156",
        "σπέρματι"
      ],
      [
        "050326",
        "σπέρματι"
      ],
      [
        "050706",
        "σπέρματι"
      ],
      [
        "060414",
        "σπέρματι"
      ],
      [
        "060417",
        "σπέρματι"
      ],
      [
        "090317",
        "σπέρματι"
      ],
      [
        "090317",
        "σπέρματι"
      ]
    ],
    "N-----GSN-": [
      [
        "040743",
        "σπέρματος"
      ],
      [
        "051324",
        "σπέρματος"
      ],
      [
        "060104",
        "σπέρματος"
      ],
      [
        "061102",
        "σπέρματος"
      ],
      [
        "160209",
        "σπέρματος"
      ],
      [
        "190217",
        "σπέρματος"
      ],
      [
        "191112",
        "σπέρματος"
      ],
      [
        "271218",
        "σπέρματος"
      ]
    ],
    "N-----DPN-": [
      [
        "090317",
        "σπέρμασι(ν)"
      ]
    ]
  },
  "occurences": 43,
  "definitions": {
    "mounce": "seed, Mt. 13:24, 27, 37, 38; semen virile, Heb. 11:11; offspring, posterity, Mt. 22:24, 25; Jn. 7:42; a seed of future generations, Rom. 9:29; in NT met. a seed or principle of spiritual life, 1 Jn. 3:9"
  }
}