{
  "forms": {
    "V-2AAI-S--": [
      [
        "031022",
        "ἀπέκρυψας"
      ]
    ],
    "V--XPPASF-": [
      [
        "070208",
        "ἀποκεκρυμμένην"
      ]
    ],
    "V--XPPGSN-": [
      [
        "100310",
        "ἀποκεκρυμμένου"
      ]
    ],
    "V--XPPASN-": [
      [
        "120127",
        "ἀποκεκρυμμένον"
      ]
    ]
  },
  "occurences": 4,
  "definitions": {
    "mounce": "to hide away; to conceal, withhold from sight or knowledge, Lk. 10:21; 1 Cor. 2:7; Eph. 3:9; Col. 1:26*"
  }
}