{
  "forms": {
    "V-3AAI-P--": [
      [
        "021205",
        "ἠτίμασαν"
      ]
    ],
    "V--AAPNPM-": [
      [
        "032012",
        "ἀτιμάσαντες"
      ]
    ],
    "V-2PAI-P--": [
      [
        "040850",
        "ἀτιμάζετε"
      ]
    ],
    "V--APN----": [
      [
        "050542",
        "ἀτιμασθῆναι"
      ]
    ],
    "V--PMN----": [
      [
        "060125",
        "ἀτιμάζεσθαι"
      ]
    ],
    "V-2PAI-S--": [
      [
        "060224",
        "ἀτιμάζεις"
      ]
    ],
    "V-2AAI-P--": [
      [
        "200207",
        "ἠτιμάσατε"
      ]
    ]
  },
  "occurences": 7,
  "definitions": {
    "mounce": "also spelled ἀτιμάω and ἀντιμόω, to dishonor, slight, Jn. 8:49; Rom. 2:23; Jas. 2:6; to treat with indignity, Mk. 12:4; Lk. 20:11; Acts 5:41; to abuse, debase, Rom. 1:24*"
  }
}