{
  "forms": {
    "V-3AAI-S--": [
      [
        "020124",
        "ἀνέκραξε(ν)"
      ],
      [
        "030434",
        "ἀνέκραξε(ν)"
      ]
    ],
    "V-3AAI-P--": [
      [
        "020650",
        "ἀνέκραξαν"
      ],
      [
        "032319",
        "ἀνέκραγον"
      ]
    ],
    "V--AAPNSM-": [
      [
        "030829",
        "ἀνακράξας"
      ]
    ]
  },
  "occurences": 5,
  "definitions": {
    "mounce": "to cry aloud, exclaim, shout, Mk. 1:23; 6:49; Lk. 4:33; 8:28; 23:18*"
  }
}