{
  "forms": {
    "A-----NSN-": [
      [
        "011927",
        "ἀδύνατον"
      ],
      [
        "021028",
        "ἀδύνατον"
      ],
      [
        "190605",
        "ἀδύνατον"
      ],
      [
        "190619",
        "ἀδύνατον"
      ],
      [
        "191005",
        "ἀδύνατον"
      ],
      [
        "191107",
        "ἀδύνατον"
      ]
    ],
    "A-----NPN-": [
      [
        "031828",
        "ἀδύνατα"
      ]
    ],
    "A-----NSM-": [
      [
        "051409",
        "ἀδύνατος"
      ]
    ],
    "A-----ASN-": [
      [
        "060804",
        "ἀδύνατον"
      ]
    ],
    "A-----GPM-": [
      [
        "061502",
        "ἀδυνάτων"
      ]
    ]
  },
  "occurences": 10
}