{
  "forms": {
    "V-3FAI-P--": [
      [
        "050707",
        "δουλώσουσι(ν)"
      ]
    ],
    "V-2API-P--": [
      [
        "060619",
        "ἐδουλώθητε"
      ]
    ],
    "V--APPNPM-": [
      [
        "060623",
        "δουλωθέντες"
      ]
    ],
    "V-3XPI-S--": [
      [
        "070716",
        "δεδούλωται"
      ],
      [
        "220220",
        "δεδούλωται"
      ]
    ],
    "V-1AAI-S--": [
      [
        "070920",
        "ἐδούλωσα"
      ]
    ],
    "V--XPPAPF-": [
      [
        "170204",
        "δεδουλωμένας"
      ]
    ]
  },
  "occurences": 7
}