{
  "forms": {
    "V-3AAS-S--": [
      [
        "011212",
        "ἐμπέσῃ"
      ],
      [
        "150307",
        "ἐμπέσῃ"
      ],
      [
        "150308",
        "ἐμπέσῃ"
      ]
    ],
    "V-3FMI-P--": [
      [
        "030640",
        "ἐμπεσοῦνται"
      ]
    ],
    "V--AAPGSM-": [
      [
        "031037",
        "ἐμπεσόντος"
      ]
    ],
    "V-3PAI-P--": [
      [
        "150610",
        "ἐμπίπτουσι(ν)"
      ]
    ],
    "V--AAN----": [
      [
        "191032",
        "ἐμπεσεῖν"
      ]
    ]
  },
  "occurences": 7,
  "definitions": {
    "mounce": "to fall into, Mt. 12:11; Lk. 14:5; to encounter, Lk. 10:36; to be involved in, 1 Tim. 3:6, 7; 6:9; εἰς χεῖρας, to fall under the chastisement of, Heb. 10:31"
  }
}