{
  "forms": {
    "V-3AAI-P--": [
      [
        "051208",
        "ἐξέπεσαν"
      ]
    ],
    "V-3AAS-P--": [
      [
        "052718",
        "ἐκπέσωσι(ν)"
      ]
    ],
    "V--AAN----": [
      [
        "052727",
        "ἐκπεσεῖν"
      ],
      [
        "052733",
        "ἐκπεσεῖν"
      ]
    ],
    "V-1AAS-P--": [
      [
        "052730",
        "ἐκπέσωμεν"
      ]
    ],
    "V-3XAI-S--": [
      [
        "060907",
        "ἐκπέπτωκε(ν)"
      ]
    ],
    "V-2AAI-P--": [
      [
        "090505",
        "ἐξεπέσατε"
      ]
    ],
    "V-3AAI-S--": [
      [
        "200112",
        "ἐξέπεσε(ν)"
      ],
      [
        "210125",
        "ἐξέπεσε(ν)"
      ]
    ],
    "V-2AAS-P--": [
      [
        "220318",
        "ἐκπέσητε"
      ]
    ]
  },
  "occurences": 10
}