{
  "forms": {
    "N-----GSF-": [
      [
        "011528",
        "τραπέζης"
      ],
      [
        "020729",
        "τραπέζης"
      ],
      [
        "031622",
        "τραπέζης"
      ],
      [
        "032222",
        "τραπέζης"
      ],
      [
        "032231",
        "τραπέζης"
      ],
      [
        "071022",
        "τραπέζης"
      ],
      [
        "071022",
        "τραπέζης"
      ]
    ],
    "N-----APF-": [
      [
        "012113",
        "τραπέζας"
      ],
      [
        "021116",
        "τραπέζας"
      ],
      [
        "040216",
        "τραπέζας"
      ]
    ],
    "N-----ASF-": [
      [
        "031924",
        "τράπεζαν"
      ],
      [
        "051635",
        "τράπεζαν"
      ]
    ],
    "N-----DPF-": [
      [
        "050603",
        "τραπέζαις"
      ]
    ],
    "N-----NSF-": [
      [
        "061110",
        "τράπεζα"
      ],
      [
        "190903",
        "τράπεζα"
      ]
    ]
  },
  "occurences": 15,
  "definitions": {
    "mounce": "a table, an eating table, Mt. 15:27; Mk. 7:28; Heb. 9:2; by impl. a meal, feast, Rom. 11:9; 1 Cor. 10:21; a table or counter of a money changer, Mt. 21:12; a bank, Lk. 19:23; by impl. pl. money matters, Acts 6:2"
  }
}